{
  "id": 10,
  "username": "Stacy_Pacocha65",
  "display_name": "Stacy Pacocha",
  "email": "Stacy.Pacocha@yahoo.com",
  "birthday": null,
  "age": 28,
  "status": "active",
  "about_me": "Viridis magni caput ars.",
  "searching_for": "Bạn tâm giao / Trò chuyện",
  "sexual_orientation": "Dị tính",
  "language": "English",
  "education": "Cử nhân",
  "religion": "Ấn Độ giáo",
  "career": "Bác sĩ",
  "height": "173",
  "location": "Lake Jazlyn",
  "zodiac": "Bảo Bình",
  "character": "Nghiêm túc",
  "character_list": [
    "Nghiêm túc"
  ],
  "communicate_style": "Thẳng thắn",
  "communicate_style_list": [
    "Thẳng thắn"
  ],
  "love_language": "Tiếp xúc cơ thể",
  "love_language_list": [
    "Tiếp xúc cơ thể"
  ],
  "future_family": "Chưa muốn có con",
  "drink": false,
  "smoke": true,
  "train": false,
  "diet": "Ăn kiêng",
  "sleep": "Người dậy sớm",
  "snu": "Không",
  "pet": "Mèo",
  "pet_list": [
    "Mèo"
  ],
  "favorite": "Du lịch",
  "favorite_list": [
    "Du lịch"
  ]
}