{
  "id": 22,
  "username": "Leola_Wilkinson26",
  "display_name": "Leola Wilkinson",
  "email": "Leola_Wilkinson49@hotmail.com",
  "birthday": null,
  "age": 53,
  "status": "active",
  "about_me": "Inventore depraedor illum cometes turbo verecundia carus adversus.",
  "searching_for": "Kết bạn mới",
  "sexual_orientation": "Đồng tính",
  "language": "Vietnamese",
  "education": "Tiến sĩ",
  "religion": "Cơ đốc giáo",
  "career": "Bác sĩ",
  "height": "153",
  "location": "Lombard",
  "zodiac": "Cự Giải",
  "character": "Nghiêm túc",
  "character_list": [
    "Nghiêm túc"
  ],
  "communicate_style": "Trầm lặng",
  "communicate_style_list": [
    "Trầm lặng"
  ],
  "love_language": "Tiếp xúc cơ thể",
  "love_language_list": [
    "Tiếp xúc cơ thể"
  ],
  "future_family": "Không muốn con",
  "drink": false,
  "smoke": true,
  "train": false,
  "diet": "Ăn chay",
  "sleep": "Người dậy sớm",
  "snu": "Có",
  "pet": "Mèo",
  "pet_list": [
    "Mèo"
  ],
  "favorite": "Yoga",
  "favorite_list": [
    "Yoga"
  ]
}