{
  "id": 41,
  "username": "Ellie.Weissnat",
  "display_name": "Ellie Weissnat",
  "email": "Ellie.Weissnat75@yahoo.com",
  "birthday": null,
  "age": 54,
  "status": "active",
  "about_me": "Spoliatio ustulo nam vicissitudo sonitus.",
  "searching_for": "Hẹn hò đơn giản / Tìm hiểu",
  "sexual_orientation": "Vô tính",
  "language": "Vietnamese",
  "education": "Tiến sĩ",
  "religion": "Phật giáo",
  "career": "Giáo viên",
  "height": "158",
  "location": "East Kaycee",
  "zodiac": "Sư Tử",
  "character": "Điềm đạm",
  "character_list": [
    "Điềm đạm"
  ],
  "communicate_style": "Thẳng thắn",
  "communicate_style_list": [
    "Thẳng thắn"
  ],
  "love_language": "Thời gian chất lượng",
  "love_language_list": [
    "Thời gian chất lượng"
  ],
  "future_family": "Không muốn con",
  "drink": true,
  "smoke": false,
  "train": true,
  "diet": "Ăn chay",
  "sleep": "Cú đêm",
  "snu": "Có",
  "pet": "Chó",
  "pet_list": [
    "Chó"
  ],
  "favorite": "Cà phê",
  "favorite_list": [
    "Cà phê"
  ]
}