{
  "id": 32,
  "username": "Florida_Koch87",
  "display_name": "Florida Koch",
  "email": "Florida_Koch@yahoo.com",
  "birthday": null,
  "age": 34,
  "status": "active",
  "about_me": "Vulgivagus censura vestigium tricesimus aduro nulla reprehenderit.",
  "searching_for": "Mối quan hệ lâu dài",
  "sexual_orientation": "Dị tính",
  "language": "Japanese",
  "education": "Trung học phổ thông",
  "religion": "Ấn Độ giáo",
  "career": "Giáo viên",
  "height": "178",
  "location": "Fort Florencio",
  "zodiac": "Xử Nữ",
  "character": "Tự tin",
  "character_list": [
    "Tự tin"
  ],
  "communicate_style": "Thẳng thắn",
  "communicate_style_list": [
    "Thẳng thắn"
  ],
  "love_language": "Tiếp xúc cơ thể",
  "love_language_list": [
    "Tiếp xúc cơ thể"
  ],
  "future_family": "Chưa muốn có con",
  "drink": true,
  "smoke": true,
  "train": true,
  "diet": "Ăn chay",
  "sleep": "Cú đêm",
  "snu": "Không",
  "pet": "Chim",
  "pet_list": [
    "Chim"
  ],
  "favorite": "Đọc sách",
  "favorite_list": [
    "Đọc sách",
    "Yoga"
  ]
}